{
	"__comment": "Made with MC Model Maker for Minecraft versions 14w26a+",
	"ambientocclusion": true,
	"textures": {
		"Staff_Diamond": "items/diamondd",
		"TableSide": "block/crafting_table_side",
		"TableTop": "block/crafting_table_top",
		"TableBottom": "block/planks_oak",
		"particle": "block/crafting_table_front"
	},
    	"display": {
        "firstperson": {
              "rotation": [ 180, 50, 160 ],
            "translation": [ 0, 7, 2 ],
            "scale": [ 1.7, 1.7, 1.7 ]
        },
     	 "thirdperson": {
            "rotation": [ 0, 90, 270 ],
            "translation": [ 0, 1, -5 ],
            "scale": [ 1.3, 1.3, 1.3 ]
        },
        "gui": {
            "rotation": [ 50, 45, 45 ],
            "translation": [ 0, 0, 0 ],
            "scale": [ 1, 1, 1 ]
        }
},
	"elements": [
		{
			"from": [ 7, -4, 7 ],
			"to": [ 9, 14, 9 ],
			"faces": {
				"north": { "uv": [ 0, 3, 2, 16 ], "texture": "#Staff_Diamond", "cullface": true },
				"south": { "uv": [ 2, 3, 4, 16 ], "texture": "#Staff_Diamond", "cullface": true },
				"east": { "uv": [ 4, 3, 6, 16 ], "texture": "#Staff_Diamond", "cullface": true },
				"west": { "uv": [ 6, 3, 8, 16 ], "texture": "#Staff_Diamond", "cullface": true },
				"up": { "uv": [ 12, 2, 14, 4 ], "texture": "#Staff_Diamond", "cullface": true },
				"down": { "uv": [ 12, 2, 14, 4 ], "texture": "#Staff_Diamond", "cullface": true }
			}
		},
		{
			"from": [ 7, 14, 7 ],
			"to": [ 9, 17, 9 ],
			"faces": {
				"north": { "uv": [ 14, 13, 16, 16 ], "texture": "#Staff_Diamond", "cullface": false },
				"south": { "uv": [ 14, 13, 16, 16 ], "texture": "#Staff_Diamond", "cullface": false },
				"east": { "uv": [ 14, 13, 16, 16 ], "texture": "#Staff_Diamond", "cullface": false },
				"west": { "uv": [ 14, 13, 16, 16 ], "texture": "#Staff_Diamond", "cullface": false },
				"up": { "uv": [ 0, 0, 0, 0 ], "texture": "#Staff_Diamond", "cullface": false },
				"down": { "uv": [ 11, 1, 15, 5 ], "texture": "#Staff_Diamond", "cullface": false }
			}
		},
		{
			"from": [ 7, 17, 9 ],
			"to": [ 9, 19, 10 ],
			"faces": {
				"north": { "uv": [ 13, 7, 15, 9 ], "texture": "#Staff_Diamond", "cullface": false },
				"south": { "uv": [ 13, 7, 15, 9 ], "texture": "#Staff_Diamond", "cullface": false },
				"east": { "uv": [ 12, 7, 13, 9 ], "texture": "#Staff_Diamond", "cullface": false },
				"west": { "uv": [ 15, 7, 16, 9 ], "texture": "#Staff_Diamond", "cullface": false },
				"up": { "uv": [ 13, 6, 15, 7 ], "texture": "#Staff_Diamond", "cullface": false },
				"down": { "uv": [ 13, 9, 15, 10 ], "texture": "#Staff_Diamond", "cullface": false }
			}
		},
		{
			"from": [ 7, 17, 6 ],
			"to": [ 9, 19, 7 ],
			"faces": {
				"north": { "uv": [ 13, 7, 15, 9 ], "texture": "#Staff_Diamond", "cullface": false },
				"south": { "uv": [ 13, 7, 15, 9 ], "texture": "#Staff_Diamond", "cullface": false },
				"east": { "uv": [ 15, 7, 16, 9 ], "texture": "#Staff_Diamond", "cullface": false },
				"west": { "uv": [ 12, 7, 13, 9 ], "texture": "#Staff_Diamond", "cullface": false },
				"up": { "uv": [ 13, 6, 15, 7 ], "texture": "#Staff_Diamond", "cullface": false },
				"down": { "uv": [ 13, 9, 15, 10 ], "texture": "#Staff_Diamond", "cullface": false }
			}
		},
		{
			"from": [ 9, 17, 7 ],
			"to": [ 10, 19, 9 ],
			"faces": {
				"north": { "uv": [ 15, 7, 16, 9 ], "texture": "#Staff_Diamond", "cullface": false },
				"south": { "uv": [ 12, 7, 13, 9 ], "texture": "#Staff_Diamond", "cullface": false },
				"east": { "uv": [ 13, 7, 15, 9 ], "texture": "#Staff_Diamond", "cullface": false },
				"west": { "uv": [ 13, 7, 15, 9 ], "texture": "#Staff_Diamond", "cullface": false },
				"up": { "uv": [ 12, 7, 13, 9 ], "texture": "#Staff_Diamond", "cullface": false },
				"down": { "uv": [ 15, 7, 16, 9 ], "texture": "#Staff_Diamond", "cullface": false }
			}
		},
		{
			"from": [ 6, 17, 7 ],
			"to": [ 7, 19, 9 ],
			"faces": {
				"north": { "uv": [ 15, 7, 16, 9 ], "texture": "#Staff_Diamond", "cullface": false },
				"south": { "uv": [ 12, 7, 13, 9 ], "texture": "#Staff_Diamond", "cullface": false },
				"east": { "uv": [ 13, 7, 15, 9 ], "texture": "#Staff_Diamond", "cullface": false },
				"west": { "uv": [ 13, 7, 15, 9 ], "texture": "#Staff_Diamond", "cullface": false },
				"up": { "uv": [ 12, 7, 13, 9 ], "texture": "#Staff_Diamond", "cullface": false },
				"down": { "uv": [ 15, 7, 16, 9 ], "texture": "#Staff_Diamond", "cullface": false }
			}
		},
		{
			"from": [ 7, 19, 7 ],
			"to": [ 9, 20, 9 ],
			"faces": {
				"north": { "uv": [ 13, 6, 15, 7 ], "texture": "#Staff_Diamond", "cullface": false },
				"south": { "uv": [ 13, 9, 15, 10 ], "texture": "#Staff_Diamond", "cullface": false },
				"east": { "uv": [ 12, 7, 13, 9 ], "texture": "#Staff_Diamond", "cullface": false },
				"west": { "uv": [ 13, 9, 15, 10 ], "texture": "#Staff_Diamond", "cullface": false },
				"up": { "uv": [ 13, 7, 15, 9 ], "texture": "#Staff_Diamond", "cullface": false },
				"down": { "uv": [ 0, 0, 0, 0 ], "texture": "#Staff_Diamond", "cullface": false }
			}
		}
	]
}